spincher/__init__.py
spincher/constents.py
Spincher-0.0.1.dist-info/LICENSE.txt
Spincher-0.0.1.dist-info/METADATA
Spincher-0.0.1.dist-info/WHEEL
Spincher-0.0.1.dist-info/top_level.txt
Spincher-0.0.1.dist-info/RECORD
