Metadata-Version: 2.1
Name: Spincher
Version: 0.0.1
Summary: spincher text editor
Home-page: https://www.baidu.com
Author: Maingift --34%--
Author-email: 323858@qq.com
License: UNKNOWN
Platform: UNKNOWN
Classifier: Programming Language :: Python :: 3
Classifier: License :: OSI Approved :: MIT License
Classifier: Operating System :: OS Independent
License-File: LICENSE.txt
